konvert/__init__.py
konvert/conversions.py
konvert/points.py
konvert/projections.py
konvert-0.1.0.dist-info/LICENSE
konvert-0.1.0.dist-info/METADATA
konvert-0.1.0.dist-info/WHEEL
konvert-0.1.0.dist-info/top_level.txt
konvert-0.1.0.dist-info/RECORD
