Metadata-Version: 2.1
Name: konvert
Version: 0.1.0
Summary: Build graphs of types connected by conversions and projections
Home-page: https://github.com/georglind/konvert
Author: Kim G L Pedersen
Author-email: georglind@gmail.com
License: ASL 2.0
Platform: UNKNOWN
Classifier: License :: OSI Approved :: Apache Software License
Classifier: Programming Language :: Python
Classifier: Programming Language :: Python :: 3
Classifier: Programming Language :: Python :: 3.6
Classifier: Programming Language :: Python :: Implementation :: CPython
Classifier: Programming Language :: Python :: Implementation :: PyPy
Requires-Python: >=3.6.0
Requires-Dist: numpy
Provides-Extra: plotting
Requires-Dist: matplotlib ; extra == 'plotting'
